textbelt_utils/__init__.py
textbelt_utils/async_client.py
textbelt_utils/client.py
textbelt_utils/config.py
textbelt_utils/exceptions.py
textbelt_utils/models.py
textbelt_utils/setup.py
textbelt_utils/utils.py
textbelt_utils-0.3.2.dist-info/LICENSE
textbelt_utils-0.3.2.dist-info/METADATA
textbelt_utils-0.3.2.dist-info/WHEEL
textbelt_utils-0.3.2.dist-info/RECORD
