Metadata-Version: 2.3
Name: textbelt-utils
Version: 0.3.2
Summary: A lightweight Python package for interacting with the Textbelt SMS API
License: MIT
Author: Chris Bassano
Author-email: chrisbassano@gmail.com
Requires-Python: >=3.8
Classifier: Development Status :: 4 - Beta
Classifier: Intended Audience :: Developers
Classifier: License :: OSI Approved :: MIT License
Classifier: Programming Language :: Python :: 3
Classifier: Programming Language :: Python :: 3.8
Classifier: Programming Language :: Python :: 3.9
Classifier: Programming Language :: Python :: 3.10
Classifier: Programming Language :: Python :: 3.11
Classifier: Programming Language :: Python :: 3.12
Provides-Extra: async
Requires-Dist: httpx[http2] (>=0.27.0) ; extra == "async"
Requires-Dist: python-dotenv (>=1.0.0)
Requires-Dist: requests (>=2.32.0,<3.0.0)
Project-URL: Homepage, https://github.com/christo4b/textbelt-utils
